xmtp_bindings-0.1.5.dist-info/RECORD
xmtp_bindings-0.1.5.dist-info/WHEEL
xmtp_bindings-0.1.5.dist-info/top_level.txt
xmtp_bindings-0.1.5.dist-info/METADATA
xmtp_bindings-0.1.5.dist-info/licenses/LICENSE
xmtp_bindings/build.py
xmtp_bindings/libxmtp.ref
xmtp_bindings/xmtpv3.py
xmtp_bindings/__init__.py
xmtp_bindings/py.typed
xmtp_bindings/libxmtpv3.dylib
