Metadata-Version: 2.4
Name: xmtp-bindings
Version: 0.1.5
Summary: Python bindings for libxmtp (XMTP v3)
License-Expression: Apache-2.0
Project-URL: Homepage, https://github.com/pierce403/xmtp-py
Project-URL: Source, https://github.com/pierce403/xmtp-py
Project-URL: Issues, https://github.com/pierce403/xmtp-py/issues
Project-URL: Documentation, https://github.com/pierce403/xmtp-py#readme
Classifier: Development Status :: 3 - Alpha
Classifier: Intended Audience :: Developers
Classifier: Programming Language :: Python :: 3
Classifier: Programming Language :: Python :: 3 :: Only
Classifier: Programming Language :: Python :: 3.10
Classifier: Programming Language :: Python :: 3.11
Classifier: Programming Language :: Python :: 3.12
Classifier: Programming Language :: Python :: 3.13
Classifier: Typing :: Typed
Requires-Python: >=3.10
License-File: LICENSE
Dynamic: license-file
